Workbook

Sheet 1. Operaciones
A1: ID_Operación | B1: Fecha | C1: Cliente | D1: Código Producto | E1: Producto | F1: Categoría | G1: País Destino | H1: Región | I1: Arancel % | J1: Clasificación | K1: Unidades | L1: Precio FOB | M1: Costo Unitario | N1: Valor FOB | O1: Costo total | P1: Utilidad | Q1: Margen | R1: Nivel de rentabilidad | S1: Nivel de operación | T1: Prioridad comercial | U1: Estado
A2: EX001 | B2: 46027 | C2: Comercial Maya | D2: P003 | E2: =VLOOKUP(D2, '2. Productos'!$A$3:$D$7, 2, FALSE()) -> Miel natural | F2: =VLOOKUP(D2, '2. Productos'!$A$3:$D$7, 3, FALSE()) -> Apícola | G2: Guatemala | H2: =VLOOKUP(G2, '3. Mercados'!$A$2:$D$7, 2, FALSE()) -> Centroamérica | I2: =VLOOKUP(G2, '3. Mercados'!$A$2:$D$7, 3, FALSE()) -> 0.03 | J2: =VLOOKUP(G2, '3. Mercados'!$A$2:$D$7, 4, FALSE()) -> Estratégico | K2: 850 | L2: 4.8 | M2: 3.2 | N2: =K2*L2 -> 4080 | O2: =K2*M2 -> 2720 | P2: =N2-O2 -> 1360 | Q2: =P2/N2 -> 0.33333333 | R2: =IF(Q2>=0.3, "Alta", IF(Q2>=0.15, "Media", "Baja")) -> Alta | S2: =IF(N2>=10000, "Grande", IF(N2>=5000, "Mediana", "Pequeña")) -> Pequeña | T2: =IF(AND(J2="Estratégico", Q2>=0.3), "Alta", IF(AND(J2="Estratégico", Q2<0.3), "Media", IF(AND(J2="Potencial", Q2>=0.3), "Media", "Baja"))) -> Alta | U2: Embarcado
A3: EX002 | B3: 46034 | C3: Global Foods | D3: P001 | E3: =VLOOKUP(D3, '2. Productos'!$A$3:$D$7, 2, FALSE()) -> Café especial | F3: =VLOOKUP(D3, '2. Productos'!$A$3:$D$7, 3, FALSE()) -> Café | G3: EE.UU. | H3: =VLOOKUP(G3, '3. Mercados'!$A$2:$D$7, 2, FALSE()) -> Norteamérica | I3: =VLOOKUP(G3, '3. Mercados'!$A$2:$D$7, 3, FALSE()) -> 0.05 | J3: =VLOOKUP(G3, '3. Mercados'!$A$2:$D$7, 4, FALSE()) -> Estratégico | K3: 1200 | L3: 6.5 | M3: 4.1 | N3: =K3*L3 -> 7800 | O3: =K3*M3 -> 4920 | P3: =N3-O3 -> 2880 | Q3: =P3/N3 -> 0.36923077 | R3: =IF(Q3>=0.3, "Alta", IF(Q3>=0.15, "Media", "Baja")) -> Alta | S3: =IF(N3>=10000, "Grande", IF(N3>=5000, "Mediana", "Pequeña")) -> Mediana | T3: =IF(AND(J3="Estratégico", Q3>=0.3), "Alta", IF(AND(J3="Estratégico", Q3<0.3), "Media", IF(AND(J3="Potencial", Q3>=0.3), "Media", "Baja"))) -> Alta | U3: Entregado
A4: EX003 | B4: 46042 | C4: Distribuidora Tica | D4: P004 | E4: =VLOOKUP(D4, '2. Productos'!$A$3:$D$7, 2, FALSE()) -> Maní procesado | F4: =VLOOKUP(D4, '2. Productos'!$A$3:$D$7, 3, FALSE()) -> Semillas | G4: Costa Rica | H4: =VLOOKUP(G4, '3. Mercados'!$A$2:$D$7, 2, FALSE()) -> Centroamérica | I4: =VLOOKUP(G4, '3. Mercados'!$A$2:$D$7, 3, FALSE()) -> 0.02 | J4: =VLOOKUP(G4, '3. Mercados'!$A$2:$D$7, 4, FALSE()) -> Estratégico | K4: 650 | L4: 8.2 | M4: 5.9 | N4: =K4*L4 -> 5330 | O4: =K4*M4 -> 3835 | P4: =N4-O4 -> 1495 | Q4: =P4/N4 -> 0.2804878 | R4: =IF(Q4>=0.3, "Alta", IF(Q4>=0.15, "Media", "Baja")) -> Media | S4: =IF(N4>=10000, "Grande", IF(N4>=5000, "Mediana", "Pequeña")) -> Mediana | T4: =IF(AND(J4="Estratégico", Q4>=0.3), "Alta", IF(AND(J4="Estratégico", Q4<0.3), "Media", IF(AND(J4="Potencial", Q4>=0.3), "Media", "Baja"))) -> Media | U4: Embarcado
A5: EX004 | B5: 46056 | C5: Iberia Foods | D5: P002 | E5: =VLOOKUP(D5, '2. Productos'!$A$3:$D$7, 2, FALSE()) -> Cacao en grano | F5: =VLOOKUP(D5, '2. Productos'!$A$3:$D$7, 3, FALSE()) -> Cacao | G5: España | H5: =VLOOKUP(G5, '3. Mercados'!$A$2:$D$7, 2, FALSE()) -> Europa | I5: =VLOOKUP(G5, '3. Mercados'!$A$2:$D$7, 3, FALSE()) -> 0.1 | J5: =VLOOKUP(G5, '3. Mercados'!$A$2:$D$7, 4, FALSE()) -> Potencial | K5: 950 | L5: 7.1 | M5: 4.8 | N5: =K5*L5 -> 6745 | O5: =K5*M5 -> 4560 | P5: =N5-O5 -> 2185 | Q5: =P5/N5 -> 0.32394366 | R5: =IF(Q5>=0.3, "Alta", IF(Q5>=0.15, "Media", "Baja")) -> Alta | S5: =IF(N5>=10000, "Grande", IF(N5>=5000, "Mediana", "Pequeña")) -> Mediana | T5: =IF(AND(J5="Estratégico", Q5>=0.3), "Alta", IF(AND(J5="Estratégico", Q5<0.3), "Media", IF(AND(J5="Potencial", Q5>=0.3), "Media", "Baja"))) -> Media | U5: Pendiente
A6: EX005 | B6: 46068 | C6: Comercial Azteca | D6: P005 | E6: =VLOOKUP(D6, '2. Productos'!$A$3:$D$7, 2, FALSE()) -> Aceite de ajonjolí | F6: =VLOOKUP(D6, '2. Productos'!$A$3:$D$7, 3, FALSE()) -> Aceites | G6: México | H6: =VLOOKUP(G6, '3. Mercados'!$A$2:$D$7, 2, FALSE()) -> Norteamérica | I6: =VLOOKUP(G6, '3. Mercados'!$A$2:$D$7, 3, FALSE()) -> 0.08 | J6: =VLOOKUP(G6, '3. Mercados'!$A$2:$D$7, 4, FALSE()) -> Potencial | K6: 500 | L6: 12.5 | M6: 8.7 | N6: =K6*L6 -> 6250 | O6: =K6*M6 -> 4350 | P6: =N6-O6 -> 1900 | Q6: =P6/N6 -> 0.304 | R6: =IF(Q6>=0.3, "Alta", IF(Q6>=0.15, "Media", "Baja")) -> Alta | S6: =IF(N6>=10000, "Grande", IF(N6>=5000, "Mediana", "Pequeña")) -> Mediana | T6: =IF(AND(J6="Estratégico", Q6>=0.3), "Alta", IF(AND(J6="Estratégico", Q6<0.3), "Media", IF(AND(J6="Potencial", Q6>=0.3), "Media", "Baja"))) -> Media | U6: Entregado
A7: EX006 | B7: 46081 | C7: Global Foods | D7: P003 | E7: =VLOOKUP(D7, '2. Productos'!$A$3:$D$7, 2, FALSE()) -> Miel natural | F7: =VLOOKUP(D7, '2. Productos'!$A$3:$D$7, 3, FALSE()) -> Apícola | G7: EE.UU. | H7: =VLOOKUP(G7, '3. Mercados'!$A$2:$D$7, 2, FALSE()) -> Norteamérica | I7: =VLOOKUP(G7, '3. Mercados'!$A$2:$D$7, 3, FALSE()) -> 0.05 | J7: =VLOOKUP(G7, '3. Mercados'!$A$2:$D$7, 4, FALSE()) -> Estratégico | K7: 1400 | L7: 4.8 | M7: 3.2 | N7: =K7*L7 -> 6720 | O7: =K7*M7 -> 4480 | P7: =N7-O7 -> 2240 | Q7: =P7/N7 -> 0.33333333 | R7: =IF(Q7>=0.3, "Alta", IF(Q7>=0.15, "Media", "Baja")) -> Alta | S7: =IF(N7>=10000, "Grande", IF(N7>=5000, "Mediana", "Pequeña")) -> Mediana | T7: =IF(AND(J7="Estratégico", Q7>=0.3), "Alta", IF(AND(J7="Estratégico", Q7<0.3), "Media", IF(AND(J7="Potencial", Q7>=0.3), "Media", "Baja"))) -> Alta | U7: Entregado
A8: EX007 | B8: 46089 | C8: Distribuidora Tica | D8: P001 | E8: =VLOOKUP(D8, '2. Productos'!$A$3:$D$7, 2, FALSE()) -> Café especial | F8: =VLOOKUP(D8, '2. Productos'!$A$3:$D$7, 3, FALSE()) -> Café | G8: Costa Rica | H8: =VLOOKUP(G8, '3. Mercados'!$A$2:$D$7, 2, FALSE()) -> Centroamérica | I8: =VLOOKUP(G8, '3. Mercados'!$A$2:$D$7, 3, FALSE()) -> 0.02 | J8: =VLOOKUP(G8, '3. Mercados'!$A$2:$D$7, 4, FALSE()) -> Estratégico | K8: 900 | L8: 6.5 | M8: 4.1 | N8: =K8*L8 -> 5850 | O8: =K8*M8 -> 3690 | P8: =N8-O8 -> 2160 | Q8: =P8/N8 -> 0.36923077 | R8: =IF(Q8>=0.3, "Alta", IF(Q8>=0.15, "Media", "Baja")) -> Alta | S8: =IF(N8>=10000, "Grande", IF(N8>=5000, "Mediana", "Pequeña")) -> Mediana | T8: =IF(AND(J8="Estratégico", Q8>=0.3), "Alta", IF(AND(J8="Estratégico", Q8<0.3), "Media", IF(AND(J8="Potencial", Q8>=0.3), "Media", "Baja"))) -> Alta | U8: Embarcado
A9: EX008 | B9: 46099 | C9: Comercial Maya | D9: P004 | E9: =VLOOKUP(D9, '2. Productos'!$A$3:$D$7, 2, FALSE()) -> Maní procesado | F9: =VLOOKUP(D9, '2. Productos'!$A$3:$D$7, 3, FALSE()) -> Semillas | G9: Guatemala | H9: =VLOOKUP(G9, '3. Mercados'!$A$2:$D$7, 2, FALSE()) -> Centroamérica | I9: =VLOOKUP(G9, '3. Mercados'!$A$2:$D$7, 3, FALSE()) -> 0.03 | J9: =VLOOKUP(G9, '3. Mercados'!$A$2:$D$7, 4, FALSE()) -> Estratégico | K9: 750 | L9: 8.2 | M9: 5.9 | N9: =K9*L9 -> 6150 | O9: =K9*M9 -> 4425 | P9: =N9-O9 -> 1725 | Q9: =P9/N9 -> 0.2804878 | R9: =IF(Q9>=0.3, "Alta", IF(Q9>=0.15, "Media", "Baja")) -> Media | S9: =IF(N9>=10000, "Grande", IF(N9>=5000, "Mediana", "Pequeña")) -> Mediana | T9: =IF(AND(J9="Estratégico", Q9>=0.3), "Alta", IF(AND(J9="Estratégico", Q9<0.3), "Media", IF(AND(J9="Potencial", Q9>=0.3), "Media", "Baja"))) -> Media | U9: Entregado
A10: EX009 | B10: 46106 | C10: Iberia Foods | D10: P005 | E10: =VLOOKUP(D10, '2. Productos'!$A$3:$D$7, 2, FALSE()) -> Aceite de ajonjolí | F10: =VLOOKUP(D10, '2. Productos'!$A$3:$D$7, 3, FALSE()) -> Aceites | G10: España | H10: =VLOOKUP(G10, '3. Mercados'!$A$2:$D$7, 2, FALSE()) -> Europa | I10: =VLOOKUP(G10, '3. Mercados'!$A$2:$D$7, 3, FALSE()) -> 0.1 | J10: =VLOOKUP(G10, '3. Mercados'!$A$2:$D$7, 4, FALSE()) -> Potencial | K10: 600 | L10: 12.5 | M10: 8.7 | N10: =K10*L10 -> 7500 | O10: =K10*M10 -> 5220 | P10: =N10-O10 -> 2280 | Q10: =P10/N10 -> 0.304 | R10: =IF(Q10>=0.3, "Alta", IF(Q10>=0.15, "Media", "Baja")) -> Alta | S10: =IF(N10>=10000, "Grande", IF(N10>=5000, "Mediana", "Pequeña")) -> Mediana | T10: =IF(AND(J10="Estratégico", Q10>=0.3), "Alta", IF(AND(J10="Estratégico", Q10<0.3), "Media", IF(AND(J10="Potencial", Q10>=0.3), "Media", "Baja"))) -> Media | U10: Embarcado
A11: EX010 | B11: 46114 | C11: Comercial Azteca | D11: P002 | E11: =VLOOKUP(D11, '2. Productos'!$A$3:$D$7, 2, FALSE()) -> Cacao en grano | F11: =VLOOKUP(D11, '2. Productos'!$A$3:$D$7, 3, FALSE()) -> Cacao | G11: México | H11: =VLOOKUP(G11, '3. Mercados'!$A$2:$D$7, 2, FALSE()) -> Norteamérica | I11: =VLOOKUP(G11, '3. Mercados'!$A$2:$D$7, 3, FALSE()) -> 0.08 | J11: =VLOOKUP(G11, '3. Mercados'!$A$2:$D$7, 4, FALSE()) -> Potencial | K11: 1100 | L11: 7.1 | M11: 4.8 | N11: =K11*L11 -> 7810 | O11: =K11*M11 -> 5280 | P11: =N11-O11 -> 2530 | Q11: =P11/N11 -> 0.32394366 | R11: =IF(Q11>=0.3, "Alta", IF(Q11>=0.15, "Media", "Baja")) -> Alta | S11: =IF(N11>=10000, "Grande", IF(N11>=5000, "Mediana", "Pequeña")) -> Mediana | T11: =IF(AND(J11="Estratégico", Q11>=0.3), "Alta", IF(AND(J11="Estratégico", Q11<0.3), "Media", IF(AND(J11="Potencial", Q11>=0.3), "Media", "Baja"))) -> Media | U11: Entregado
A12: EX011 | B12: 46122 | C12: Global Foods | D12: P004 | E12: =VLOOKUP(D12, '2. Productos'!$A$3:$D$7, 2, FALSE()) -> Maní procesado | F12: =VLOOKUP(D12, '2. Productos'!$A$3:$D$7, 3, FALSE()) -> Semillas | G12: EE.UU. | H12: =VLOOKUP(G12, '3. Mercados'!$A$2:$D$7, 2, FALSE()) -> Norteamérica | I12: =VLOOKUP(G12, '3. Mercados'!$A$2:$D$7, 3, FALSE()) -> 0.05 | J12: =VLOOKUP(G12, '3. Mercados'!$A$2:$D$7, 4, FALSE()) -> Estratégico | K12: 1300 | L12: 8.2 | M12: 5.9 | N12: =K12*L12 -> 10660 | O12: =K12*M12 -> 7670 | P12: =N12-O12 -> 2990 | Q12: =P12/N12 -> 0.2804878 | R12: =IF(Q12>=0.3, "Alta", IF(Q12>=0.15, "Media", "Baja")) -> Media | S12: =IF(N12>=10000, "Grande", IF(N12>=5000, "Mediana", "Pequeña")) -> Grande | T12: =IF(AND(J12="Estratégico", Q12>=0.3), "Alta", IF(AND(J12="Estratégico", Q12<0.3), "Media", IF(AND(J12="Potencial", Q12>=0.3), "Media", "Baja"))) -> Media | U12: Entregado
A13: EX012 | B13: 46130 | C13: Comercial Maya | D13: P001 | E13: =VLOOKUP(D13, '2. Productos'!$A$3:$D$7, 2, FALSE()) -> Café especial | F13: =VLOOKUP(D13, '2. Productos'!$A$3:$D$7, 3, FALSE()) -> Café | G13: Guatemala | H13: =VLOOKUP(G13, '3. Mercados'!$A$2:$D$7, 2, FALSE()) -> Centroamérica | I13: =VLOOKUP(G13, '3. Mercados'!$A$2:$D$7, 3, FALSE()) -> 0.03 | J13: =VLOOKUP(G13, '3. Mercados'!$A$2:$D$7, 4, FALSE()) -> Estratégico | K13: 700 | L13: 6.5 | M13: 4.1 | N13: =K13*L13 -> 4550 | O13: =K13*M13 -> 2870 | P13: =N13-O13 -> 1680 | Q13: =P13/N13 -> 0.36923077 | R13: =IF(Q13>=0.3, "Alta", IF(Q13>=0.15, "Media", "Baja")) -> Alta | S13: =IF(N13>=10000, "Grande", IF(N13>=5000, "Mediana", "Pequeña")) -> Pequeña | T13: =IF(AND(J13="Estratégico", Q13>=0.3), "Alta", IF(AND(J13="Estratégico", Q13<0.3), "Media", IF(AND(J13="Potencial", Q13>=0.3), "Media", "Baja"))) -> Alta | U13: Pendiente
... A101: EX100 | B101: 46150 | C101: Comercial Azteca | D101: P001 | E101: =VLOOKUP(D101, '2. Productos'!$A$3:$D$7, 2, FALSE()) -> Café especial | F101: =VLOOKUP(D101, '2. Productos'!$A$3:$D$7, 3, FALSE()) -> Café | G101: México | H101: =VLOOKUP(G101, '3. Mercados'!$A$2:$D$7, 2, FALSE()) -> Norteamérica | I101: =VLOOKUP(G101, '3. Mercados'!$A$2:$D$7, 3, FALSE()) -> 0.08 | J101: =VLOOKUP(G101, '3. Mercados'!$A$2:$D$7, 4, FALSE()) -> Potencial | K101: 1170 | L101: 6.5 | M101: 4.1 | N101: =K101*L101 -> 7605 | O101: =K101*M101 -> 4797 | P101: =N101-O101 -> 2808 | Q101: =P101/N101 -> 0.36923077 | R101: =IF(Q101>=0.3, "Alta", IF(Q101>=0.15, "Media", "Baja")) -> Alta | S101: =IF(N101>=10000, "Grande", IF(N101>=5000, "Mediana", "Pequeña")) -> Mediana | T101: =IF(AND(J101="Estratégico", Q101>=0.3), "Alta", IF(AND(J101="Estratégico", Q101<0.3), "Media", IF(AND(J101="Potencial", Q101>=0.3), "Media", "Baja"))) -> Media | U101: Entregado

Sheet 2. Productos
A1: Columna1 | B1: Columna2 | C1: Columna3 | D1: Columna4
A2: Código | B2: Producto | C2: Categoría | D2: Unidad de Medida
A3: P001 | B3: Café especial | C3: Café | D3: Kg
A4: P002 | B4: Cacao en grano | C4: Cacao | D4: Kg
A5: P003 | B5: Miel natural | C5: Apícola | D5: Kg
A6: P004 | B6: Maní procesado | C6: Semillas | D6: Kg
A7: P005 | B7: Aceite de ajonjolí | C7: Aceites | D7: Litro

Sheet 3. Mercados
A1: País | B1: Región | C1: Arancel % | D1: Clasificación
A2: EE.UU. | B2: Norteamérica | C2: 0.05 | D2: Estratégico
A3: México | B3: Norteamérica | C3: 0.08 | D3: Potencial
A4: Guatemala | B4: Centroamérica | C4: 0.03 | D4: Estratégico
A5: Costa Rica | B5: Centroamérica | C5: 0.02 | D5: Estratégico
A6: El Salvador | B6: Centroamérica | C6: 0.02 | D6: Potencial
A7: España | B7: Europa | C7: 0.1 | D7: Potencial

Sheet  Respuestas
A1: Nº | B1: Pregunta de Análisis | C1: Resultado / Fórmula en Excel
A2: 1 | B2: ¿Cuántas operaciones internacionales se realizaron? | C2: =COUNTA('1. Operaciones'!A2:A101) -> 100
A3: 2 | B3: ¿Cuántas operaciones están pendientes? | C3: =COUNTIF('1. Operaciones'!U2:U101, "Pendiente") -> 15
A4: 3 | B4: ¿Cuál es el país con mayor cantidad de operaciones? | C4: Guatemala (20 operaciones)
A5: 4 | B5: ¿Cuál es el país que genera mayor valor FOB? | C5: EE.UU. ($168,745.00)
A6: 5 | B6: ¿Cuál es el producto más exportado por unidades? | C6: Café especial (26,180 unidades)
A7: 6 | B7: ¿Cuál es el producto que genera mayor utilidad? | C7: Café especial ($62,832.00)
A8: 7 | B8: ¿Cuál es el mercado con mayor margen promedio? | C8: EE.UU. (33.04%)
A9: 8 | B9: ¿Cuántas operaciones tienen rentabilidad alta? | C9: =COUNTIF('1. Operaciones'!R2:R101, "Alta") -> 82
A10: 9 | B10: ¿Cuánto se exportó hacia Centroamérica? | C10: =SUMIF('1. Operaciones'!H2:H101, "Centroamérica", '1. Operaciones'!N2:N101) -> 232879
A11: 10 | B11: ¿Cuánto se exportó hacia Norteamérica? | C11: =SUMIF('1. Operaciones'!H2:H101, "Norteamérica", '1. Operaciones'!N2:N101) -> 289058
A12: 11 | B12: ¿Cuánto se exportó hacia Europa? | C12: =SUMIF('1. Operaciones'!H2:H101, "Europa", '1. Operaciones'!N2:N101) -> 136328
A13: 12 | B13: ¿Qué operaciones tienen prioridad comercial alta? | C13: 48 operaciones (Ver columna T en Operaciones)
A14: 13 | B14: ¿Qué clientes generan mayor valor de exportación? | C14: Global Foods ($168,745.00), Iberia Foods ($136,328.00)
A15: 14 | B15: ¿Qué operaciones requieren atención por estar pendientes? | C15: 15 operaciones específicas (EX004, EX012, etc.)

Sheet  Tablas y Gráficos
A1: TABLA DINÁMICA 1: Valor FOB por País | B1: Columna1
A2: País Destino | B2: Valor FOB Total (US$)
A3: Costa Rica | B3: =SUMIF('1. Operaciones'!$G$2:$G$101, A3, '1. Operaciones'!$N$2:$N$101) -> 113544
A4: EE.UU. | B4: =SUMIF('1. Operaciones'!$G$2:$G$101, A4, '1. Operaciones'!$N$2:$N$101) -> 168745
A5: España | B5: =SUMIF('1. Operaciones'!$G$2:$G$101, A5, '1. Operaciones'!$N$2:$N$101) -> 136328
A6: Guatemala | B6: =SUMIF('1. Operaciones'!$G$2:$G$101, A6, '1. Operaciones'!$N$2:$N$101) -> 119335
A7: México | B7: =SUMIF('1. Operaciones'!$G$2:$G$101, A7, '1. Operaciones'!$N$2:$N$101) -> 120313
A9: TABLA DINÁMICA 2: Utilidad por Producto | B9: Columna1
A10: Producto | B10: Utilidad Total (US$)
A11: Aceite de ajonjolí | B11: =SUMIF('1. Operaciones'!$E$2:$E$101, A11, '1. Operaciones'!$P$2:$P$101) -> 42218
A12: Cacao en grano | B12: =SUMIF('1. Operaciones'!$E$2:$E$101, A12, '1. Operaciones'!$P$2:$P$101) -> 36800
A13: Café especial | B13: =SUMIF('1. Operaciones'!$E$2:$E$101, A13, '1. Operaciones'!$P$2:$P$101) -> 62832
A14: Maní procesado | B14: =SUMIF('1. Operaciones'!$E$2:$E$101, A14, '1. Operaciones'!$P$2:$P$101) -> 33534
A15: Miel natural | B15: =SUMIF('1. Operaciones'!$E$2:$E$101, A15, '1. Operaciones'!$P$2:$P$101) -> 38688
A17: TABLA DINÁMICA 3: Ventas (Valor FOB) por Región | B17: Columna1
A18: Región | B18: Valor FOB Total (US$)
A19: Centroamérica | B19: =SUMIF('1. Operaciones'!$H$2:$H$101, A19, '1. Operaciones'!$N$2:$N$101) -> 232879
A20: Europa | B20: =SUMIF('1. Operaciones'!$H$2:$H$101, A20, '1. Operaciones'!$N$2:$N$101) -> 136328
A21: Norteamérica | B21: =SUMIF('1. Operaciones'!$H$2:$H$101, A21, '1. Operaciones'!$N$2:$N$101) -> 289058
A23: TABLA DINÁMICA 4: Operaciones por Clasificación de Prioridad | B23: Columna1
A24: Prioridad Comercial | B24: Cantidad de Operaciones
A25: Alta | B25: =COUNTIF('1. Operaciones'!$T$2:$T$101, A25) -> 48
A26: Baja | B26: =COUNTIF('1. Operaciones'!$T$2:$T$101, A26) -> 6
A27: Media | B27: =COUNTIF('1. Operaciones'!$T$2:$T$101, A27) -> 46

Sheet  Interpretaciones
A1: Gráfico Analítico | B1: Interpretación Gerencial / Comercial | C1: Interpretación Gerencial / Comercial
A2: 1. Valor FOB por País | B2: Estados Unidos se consolida como el principal mercado de exportación de Nica Export Trading, S.A., generando US$ 168,745.00, impulsado fuertemente por la demanda de café especial. España e incluso mercados regionales como México y Guatemala también muestran volúmenes muy sólidos, evidenciando una diversificación comercial favorable pero con claro liderazgo norteamericano.
A3: 2. Utilidad por Producto | B3: El Café Especial encabeza de manera absoluta la generación de utilidad neta para la empresa (US$ 62,832.00), seguido por el Aceite de Ajonjolí y la Miel Natural. Esto demuestra que los productos de valor agregado agroindustrial y de alta calidad son los verdaderos motores de rentabilidad, superando a los commodities básicos en términos de margen porcentual.
A4: 3. Valor FOB por Región | B4: Norteamérica representa la región con mayor valor de exportación (US$ 289,058.00), seguida de cerca por Centroamérica (US$ 232,879.00) y Europa (US$ 136,328.00). La cercanía logística con Centroamérica facilita un flujo constante de operaciones, mientras que Norteamérica concentra el mayor valor monetario gracias a pedidos de mayor escala y precios FOB superiores.
